{"sections":{"main":{"type":"main-product","blocks":{"title":{"type":"title","settings":{}},"price":{"type":"price","settings":{"show_tax_and_shipping":true,"enable_product_reviews_by_price":true}},"divider":{"type":"divider","disabled":true,"settings":{"show_in_quickbuy":false}},"variant_picker_AapW9m":{"type":"variant-picker","settings":{"show_single":true,"selector_style":"listed","enable_dynamic_availability":true,"enable_size_chart":false,"size_chart_variant":"","size_chart_page":""}},"bd48926f-a490-4678-ae48-a8ad6210018b":{"type":"accordion","disabled":true,"settings":{"title":"Specification","icon":"","content":"<p>Collapsible tab content<\/p>","page":"specification","custom_liquid":"","open":false,"show_in_quickbuy":false}},"accordion_GggAcn":{"type":"accordion","disabled":true,"settings":{"title":"Compatible Device","icon":"","content":"<p>XbotGo is compatible with smartphones that feature either Qualcomm Snapdragon 888 CPU or newer processors and Apple A12 CPU or newer processors. Here are the recommended phone models that meet these criteria:<\/p><ul><li><strong>Apple:<\/strong><br\/>iPhone 11 or later models<\/li><li><strong>Samsung:<\/strong><br\/>Samsung Galaxy S21\/S22\/S23 series, Galaxy Z Flip3, Z Flip4, Samsung W22, W23 Flip<\/li><li><strong>Google:<\/strong><br\/>Google Pixel 7\/7Pro, Pixel 8<\/li><li><strong> Huawei: <\/strong><br\/>Huawei Mate 40\/Mate 50  series, Huawei P50\/P60 series<\/li><li><strong>Xiaomi: <\/strong><br\/>Xiaomi 11\/12\/13\/14 series<\/li><li><strong>OnePlus:<\/strong><br\/>OnePlus 9\/10\/11\/12 series, OnePlus Ace Pro<\/li><li><strong>Sony:<\/strong><br\/>Xperia PRO-I, Xperia 1 III, Xperia 1 Ⅳ, Xperia 5 III, Xperia 5 Ⅳ<\/li><li><strong>Redmi:<\/strong><br\/>Redmi K50\/K60 series<\/li><li><strong>iQOO:<\/strong> 10\/11\/12 series<\/li><li><strong>RealMe:<\/strong> GT5<\/li><li><strong>Vivo:<\/strong> X80\/X90\/X100 <\/li><li><strong>Honor:<\/strong><br\/>Honor Magic4\/Magic5<\/li><\/ul><p><\/p>","page":"","custom_liquid":"","open":false,"show_in_quickbuy":false}},"7467f53c-d35e-4c16-8c8a-5567dc57427b":{"type":"accordion","disabled":true,"settings":{"title":"User Manual","icon":"","content":"","page":"user-manual","custom_liquid":"","open":false,"show_in_quickbuy":true}},"description":{"type":"description","settings":{"show_in_tab":true,"open_tab":false,"icon":"","show_in_quickbuy":true}},"36b4455f-d340-4f5a-89bc-26827832679f":{"type":"sharing","settings":{"show_twitter":true,"show_facebook":true,"show_pinterest":true}},"buy_buttons_wgnajw":{"type":"buy-buttons","settings":{"show_quantity_selector":true,"enable_payment_button":true,"show_backorder_text":false,"show_pickup_availability":true,"show_gift_card_recipient":false}}},"block_order":["title","price","divider","variant_picker_AapW9m","bd48926f-a490-4678-ae48-a8ad6210018b","accordion_GggAcn","7467f53c-d35e-4c16-8c8a-5567dc57427b","description","36b4455f-d340-4f5a-89bc-26827832679f","buy_buttons_wgnajw"],"settings":{"show_breadcrumbs":true,"select_first_variant":true,"show_location_underneath":false,"inventory_transfers_enable":false,"enable_sticky_columns":false,"enable_sticky_atc":false,"sticky_atc_position":"end","sticky_atc_mobile":true,"sticky_atc_behavior":"add_to_cart","sticky_atc_button_style":"secondary","gallery_size":"medium","gallery_layout":"carousel-under","enable_zoom":false,"show_alt_text":false,"alt_text_icon":"","enable_video_autoplay":false,"enable_video_looping":false,"enable_media_grouping":false,"media_grouping_option":"Color,Colour,Couleur,Farbe"}},"rich_text_iKytk4":{"type":"rich-text","blocks":{"heading_TYbRHf":{"type":"heading","settings":{"title":"Rich text","use_h1":false}},"text_UWG7kT":{"type":"text","disabled":true,"settings":{"text":"<p><strong>Protect Your Investment with XbotGo’s One-Year Warranty<\/strong><\/p><p>Our One-Year Warranty offers comprehensive coverage for your XbotGo Sports Gimbal Stabilizer or XbotGo Chameleon.<\/p><p><br\/><\/p><p><br\/><br\/>12-Month Coverage Period:<br\/>Complete Protection:<br\/>Free Replacement:<br\/>Shipping Costs:<br\/><br\/>support@XbotGo.com<br\/><br\/><br\/><\/p>","enlarge_text":true}}},"block_order":["heading_TYbRHf","text_UWG7kT"],"disabled":true,"settings":{"height":"medium","text_alignment":"center","full_width":false,"color_scheme":"default"}},"related-products":{"type":"related-products","settings":{"title":"You may also like","show_vendor":false,"grid":4}},"video_cqpjhd":{"type":"video","blocks":{"heading_p8raNc":{"type":"heading","settings":{"title":"XbotGo","heading_max_width":15,"title_size":84,"title_size_mobile":32,"use_h1":false}},"text_YLdX7j":{"type":"text","settings":{"text":"<p>AI Powered Sports Auto Tracking<\/p>","enlarge_text":true}},"play_button_kkB6gh":{"type":"play-button","settings":{}}},"block_order":["heading_p8raNc","text_YLdX7j","play_button_kkB6gh"],"settings":{"video_shopify":"shopify:\/\/files\/videos\/video(17).mp4","video_external":"https:\/\/www.youtube.com\/watch?v=_9VUPq3SxOc","video_description":"","text_alignment":"center center","full_width":true,"overlay_style":"shadow"}},"image_with_text_r4tdT7":{"type":"image-with-text","settings":{"image":"shopify:\/\/shop_images\/homepagemosaic-2.jpg","image_2":"shopify:\/\/shop_images\/xbotgo_homepage_record_1.jpg","image_width":700,"image_link":"","image_position":"left","text_alignment":"left","color_scheme":"default"}},"image_with_text_HtN6iV":{"type":"image-with-text","disabled":true,"settings":{"image":"shopify:\/\/shop_images\/reid_mode.webp","image_2":"shopify:\/\/shop_images\/key_player_tracking.png","image_width":700,"image_link":"","image_position":"right","text_alignment":"left","color_scheme":"default"}},"image_with_text_q7bTBP":{"type":"image-with-text","disabled":true,"settings":{"image":"shopify:\/\/shop_images\/xbotgo_Gimbal_banner.webp","image_2":"shopify:\/\/shop_images\/xbotgohomepagemosaic-4.jpg","image_width":700,"image_link":"","image_position":"left","text_alignment":"left","color_scheme":"default"}},"image_with_text_overlay_nA6XHz":{"type":"image-with-text-overlay","settings":{"image":"shopify:\/\/shop_images\/Xbotgo_homepage_download.png","mobile_image":"shopify:\/\/shop_images\/xbotgo-MB-APP1.jpg","height":"fixed","height_desktop":600,"height_mobile":460,"image_link":"","full_width":true,"text_alignment":"top right","mobile_overlay_under":false,"overlay_style":"shadow"}},"collapsible_tabs_PjXBqN":{"type":"collapsible-tabs","blocks":{"question_89dEn6":{"type":"question","settings":{"title":"Compatible Device","answer":"<p>XbotGo is compatible with smartphones that feature either Qualcomm Snapdragon 888 CPU or newer processors and Apple A12 CPU or newer processors. Here are the recommended phone models that meet these criteria:<\/p><ul><li><strong>Apple:<\/strong><br\/>iPhone 11 or later models<\/li><li><strong>Samsung:<\/strong><br\/>Samsung Galaxy S21\/S22\/S23 series, Galaxy Z Flip3, Z Flip4, Samsung W22, W23 Flip<\/li><li><strong>Google:<\/strong><br\/>Google Pixel 7\/7Pro, Pixel 8<\/li><li><strong> Huawei: <\/strong><br\/>Huawei Mate 40\/Mate 50  series, Huawei P50\/P60 series<\/li><li><strong>Xiaomi: <\/strong><br\/>Xiaomi 11\/12\/13\/14 series<\/li><li><strong>OnePlus:<\/strong><br\/>OnePlus 9\/10\/11\/12 series, OnePlus Ace Pro<\/li><li><strong>Sony:<\/strong><br\/>Xperia PRO-I, Xperia 1 III, Xperia 1 Ⅳ, Xperia 5 III, Xperia 5 Ⅳ<\/li><li><strong>Redmi:<\/strong><br\/>Redmi K50\/K60 series<\/li><li><strong>iQOO:<\/strong> 10\/11\/12 series<\/li><li><strong>RealMe:<\/strong> GT5<\/li><li><strong>Vivo:<\/strong> X80\/X90\/X100 <\/li><li><strong>Honor:<\/strong><br\/>Honor Magic4\/Magic5<\/li><\/ul><p><\/p>"}},"question_ehTXEm":{"type":"question","settings":{"title":"Supported Sports","answer":""}},"question_6rCXYg":{"type":"question","settings":{"title":"User Manual","answer":""}}},"block_order":["question_89dEn6","question_ehTXEm","question_6rCXYg"],"settings":{"title":""}},"gallery_nYdExc":{"type":"gallery","settings":{"grid_desktop":2,"grid_mobile":"1","height":"fixed","desktop_image_height":460,"mobile_image_height":510,"title_size":30,"title_size_mobile":20,"enable_margin":true,"enable_row_spacing":true,"full_width":false,"color_scheme":"default","enable_carousel":true,"overlay_style":"full","button_style":"primary"}},"slideshow_9CUacj":{"type":"slideshow","blocks":{"image_MGpNPJ":{"type":"image","settings":{"slide_link":"","subheading":"Tell your story","title":"Two line\nslide heading","heading_max_width":15,"title_size":84,"title_size_mobile":46,"use_h1":false,"text":"<p>And optional subtext<\/p>","enlarge_text":true,"button_label_1":"Shop this","button_url_1":"","button_label_2":"Shop all","button_url_2":"","text_alignment":"center center"}},"image_hJdwnr":{"type":"image","settings":{"slide_link":"","subheading":"Tell your story","title":"Two line\nslide heading","heading_max_width":15,"title_size":84,"title_size_mobile":46,"use_h1":false,"text":"<p>And optional subtext<\/p>","enlarge_text":true,"button_label_1":"Shop this","button_url_1":"","button_label_2":"Shop all","button_url_2":"","text_alignment":"center center"}}},"block_order":["image_MGpNPJ","image_hJdwnr"],"disabled":true,"settings":{"height":"fixed","height_desktop":600,"height_mobile":460,"full_width":true,"mobile_overlay_under":false,"overlay_style":"shadow","transition":"fade","navigation":"arrows","autoplay":true,"autoplay_speed":7,"accessibility_info":""}},"video_KiWPna":{"type":"video","disabled":true,"settings":{"video_external":"https:\/\/www.youtube.com\/watch?v=_9VUPq3SxOc","video_description":"","text_alignment":"center center","full_width":true,"overlay_style":"shadow"}},"judgeme_section_review_widget_bb26":{"type":"apps","blocks":{"judgeme_review_widget_2d4d6566":{"type":"shopify:\/\/apps\/judge-me-reviews\/blocks\/review_widget\/61ccd3b1-a9f2-4160-9fe9-4fec8413e5d8","disabled":true,"settings":{}},"growave_loyalty_wishlist_block_product_review_widget_9an7YA":{"type":"shopify:\/\/apps\/growave-loyalty-wishlist\/blocks\/block.product.reviewWidget\/b3d2efbe-110a-4e27-84a8-1f2ed63996a4","settings":{}}},"block_order":["judgeme_review_widget_2d4d6566","growave_loyalty_wishlist_block_product_review_widget_9an7YA"],"settings":{"full_width":false,"show_space":true}},"gallery_34iDqA":{"type":"gallery","disabled":true,"settings":{"grid_desktop":2,"grid_mobile":"1","height":"fixed","desktop_image_height":460,"mobile_image_height":400,"title_size":30,"title_size_mobile":22,"enable_margin":true,"enable_row_spacing":true,"full_width":false,"color_scheme":"default","enable_carousel":true,"overlay_style":"full","button_style":"primary"}},"logo_list_KfgaGA":{"type":"logo-list","disabled":true,"settings":{"title":"Logo list","image_opacity":75,"color_scheme":"default"}},"164849540210eed2b4":{"type":"collapsible-tabs","blocks":{"16484954029e3005e0-0":{"type":"question","settings":{"title":"What is XbotGo?","answer":"<p>XbotGo is a smart tracking system designed for sports enthusiasts and their families. We can turn an iPhone into a fully automated camera to capture team sports with ease. Simple put your iPhone on our gimbal, along with Xbot Go App together, the system can automatically follow, record and live stream sports games like basketball and soccer games, with minimum interventions.<\/p>"}},"16484954029e3005e0-1":{"type":"question","settings":{"title":"How does XbotGo follow and track?","answer":"<p>We use AI technology to detect the position of the ball and players, analyze the speed, pose and actions of players. Our patented algorithm will decide where the action is based on the information analyzed, and control the gimbal to follow through. In particular, all these are completed on smartphones real time. Even if the phone is not connected to Internet, it is still able to track and record. Please find demo videos at <a href=\"https:\/\/www.youtube.com\/@XbotGo\">https:\/\/www.youtube.com\/@XbotGo<\/a>. All demos are shared by our real users.<\/p>"}},"c46f3672-eb94-44c3-b6e4-35e58c0d843a":{"type":"question","settings":{"title":"How to set up XbotGo gimbal?","answer":"<p>Please have the following ready before set up:<\/p><p>- XbotGo Gimbal<\/p><p>- iPhone X or a newer model with iOS 14 or newer<\/p><p>- XbotGo App (downloaded from Apple App Store)<\/p><p>- Tripod (sold separately) or any other tripod with 1\/4” head in screw<\/p><p>Put iPhone on Xbot Blink Focos gimbal, and setup the gimbal on a tripod on the side of the sports field. Open Blink Focos App, connect App with the gimbal, and then click the recording button and you can just relax. Xbot Blink Focos system will automatically track players, follow through the game, record it, and\/or live stream it to whoever you want to share.<\/p><p><br\/>Note: we recommend the gimbal to be placed near the center line of the sports field. Otherwise, the tracking performance would be compromised.<\/p>"}},"8d9547d8-e89f-4d94-bfe5-1e71802e8ca3":{"type":"question","settings":{"title":"What sports can XbotGo support?","answer":"<p>XbotGo can support basketball and soccer games. For basketball games, it supports half court and full court tracking. For soccer games, it supports 5x5, 7x7, 9x9, and 11x11 fields. It will  cover more team sports, and adding more features like smart video editing and recording with multiple cameras (Focos Pro).<\/p>"}},"1f609b6d-eeb9-42b8-baf3-35f7a3e28ed7":{"type":"question","settings":{"title":"What phones does XbotGo support?","answer":"<p>iOS: iPhone 11 or a newer model with iOS 14 or above. iPhone X works, but can be slow.<\/p><p>Android: Samsung Galaxy S21\/S22\/S23 series,Galaxy Z Flip3, Z Flip4, Samsung W22,W23 Flip.<\/p><p>Google Pixel 7\/7 Pro.<\/p><p>Huawei Mate 40\/Mate 50 series, Huawei P50\/P60 series.<\/p><p>Xiaomi 11\/12\/13 series, Xiaomi mix4, Xiaomi MIX FOLD.<\/p><p>OnePlus 9\/10\/11 series, OnePlus Ace Pro.<\/p><p>Xperia PRO-l, Xperia 1 ll, Xperia 1 IV, Xperia 5 ll, Xperia 5 IV.<\/p><p>Redmi K50\/K60 series.<\/p><p>Honor Magic3\/Magic4 series, Honor X40 GT, Honor 80 SE.<\/p><p>Search Xbot Go on Google Play.<\/p>"}},"e16b96d4-a107-4e6d-ba68-4f37edabea45":{"type":"question","settings":{"title":"Do you support DSLR or mirrorless camera?","answer":"<p>XbotGo app does not support DSLR, mirrorless camera.<\/p>"}},"2f636423-96e0-473f-99cf-b7a19c0c1f9b":{"type":"question","settings":{"title":"Can XbotGo gimbal be used as a handheld stabilizer?","answer":"<p>Yes. Even though XbotGo is designed to follow and record team sport games automatically on a tripod, it can be doubled as a regular handheld stabilizer for any occasions as well. <a href=\"https:\/\/apps.apple.com\/us\/app\/gimbal-pro\/id1353756075\" target=\"_blank\" title=\"https:\/\/apps.apple.com\/us\/app\/gimbal-pro\/id1353756075\">Download the Gimbal Pro app<\/a> for more features.<\/p>"}},"535dc233-e221-48be-be61-c9ee82fee82d":{"type":"question","settings":{"title":"Where do you ship products from?","answer":"<p>We are based in Mountain View, California. However, we have warehouses in the United States, Australia, Canada, the United Kingdom, and Germany, and we provide free shipping within the USA,, AU, DE, FR, ES, IT, PL, NL. We provide international shipping with fees and deliver in about 12 business days. <\/p>"}},"426b6d1f-994e-42eb-a28c-918da708386b":{"type":"question","settings":{"title":"What is the product warranty and what’s the return policy?","answer":"<p>XbotGo provides 1-year warranty. We also provide 30-day money-back guarantee. Please check the <a href=\"\/policies\/refund-policy\" title=\"Refund Policy\">return policy<\/a> here for more details.<\/p>"}},"6c37205c-6578-4ac2-9e85-70e9e1f48d75":{"type":"question","settings":{"title":"What tripod should I use?","answer":"<p>If you are trying to record sports on a small field such as basketball court or 5v5 soccer field, you could choose our portable <a href=\"\/products\/xbotgo-gimbal-t1-tripod-45inch\" title=\"XbotGo Gimbal T1 Tripod\">XbotGo Gimbal T1 Tripod<\/a> which is about 4 feet tall and super easy to fold and unfold. <\/p><p>On the other hand, if your goal is mainly for activities on a large filed such as 9v9 or 11v11 soccer, we highly recommend you use a 12 ft or taller tripod. It will give you a better tracking performance and a much better view angle. We are still working on Blink tripod T4 and it should be launched on US market early Oct. <\/p><p>In both cases, the customized tripods should provide a great user experience. That being said, you could also choose a third-party tripod. Look for 1\/4\" screw in head. The majority of tripods on the market should support that and thus compatible with XbotGo gimbal. <\/p>"}},"8a49daa0-88fd-42dd-863b-dd95d7b6316d":{"type":"question","settings":{"title":"How does cloud storage work?","answer":"<p>For now, we wouldn’t charge anything for the cloud storage. Feel free to upload your videos there and share with your families or friends.<\/p>"}},"4ca3aea8-f684-48b4-8d9b-fc7da14b2ace":{"type":"question","settings":{"title":"Can XbotGo gimbal track individual player?","answer":"<p>The single mode has now gone live. It tracks the person closest to the camera, usually within a distance of about ten meters.<\/p>"}},"07b41f62-bdf9-43b2-92de-10101c46bd57":{"type":"question","settings":{"title":"What if I have questions and feedbacks?","answer":"<p>You could let us know your feedback or even participate our Blink Beta program to help test new sports or new features. Email <a href=\"mailto:support@blinktech.us\">support@blinktech.us<\/a> for more information. <\/p>"}},"534eda19-5504-4e68-9389-6c6c042b20e0":{"type":"question","settings":{"title":"Is there any subscription fees?","answer":"<p>We don't charge subscription fee and there's no any hidden fees beyond the charge for the hardware.<\/p>"}}},"block_order":["16484954029e3005e0-0","16484954029e3005e0-1","c46f3672-eb94-44c3-b6e4-35e58c0d843a","8d9547d8-e89f-4d94-bfe5-1e71802e8ca3","1f609b6d-eeb9-42b8-baf3-35f7a3e28ed7","e16b96d4-a107-4e6d-ba68-4f37edabea45","2f636423-96e0-473f-99cf-b7a19c0c1f9b","535dc233-e221-48be-be61-c9ee82fee82d","426b6d1f-994e-42eb-a28c-918da708386b","6c37205c-6578-4ac2-9e85-70e9e1f48d75","8a49daa0-88fd-42dd-863b-dd95d7b6316d","4ca3aea8-f684-48b4-8d9b-fc7da14b2ace","07b41f62-bdf9-43b2-92de-10101c46bd57","534eda19-5504-4e68-9389-6c6c042b20e0"],"disabled":true,"settings":{"title":"Let's Answer Your Questions"}}},"order":["main","rich_text_iKytk4","related-products","video_cqpjhd","image_with_text_r4tdT7","image_with_text_HtN6iV","image_with_text_q7bTBP","image_with_text_overlay_nA6XHz","collapsible_tabs_PjXBqN","gallery_nYdExc","slideshow_9CUacj","video_KiWPna","judgeme_section_review_widget_bb26","gallery_34iDqA","logo_list_KfgaGA","164849540210eed2b4"]}